<?xml version="1.0" encoding="UTF-8"?>
<xml xmlns="https://developers.google.com/blockly/xml">
  <block type="wait_input" id="GENERATED_ID" data-blockNo="1">
    <mutation timeout="-1"></mutation>
    <!-- timeout (タイムアウト): 等待超时时间。flow.xml示例为-1, quickfcpr.md中单位为ms, 范围0~300000 (0为无限)。 -->
    <!-- 若遵循quickfcpr.md, timeout应为毫秒值, e.g., timeout="0" for 无限等待 or timeout="5000" for 5s -->
    <!-- 此处采用 flow.xml 的 -1 形式，可能代表无限或默认。 -->
    <!-- 有效范围(ms): 0 ~ 300000 -->
    <!-- 初期値(ms): 0 -->
    <!-- 示例(xml): -1 -->
    <field name="input_pin_name">
      <!-- input_pin_name (入力ポート名/番号): 等待的机器人本体IO输入端口的名称或编号。 -->
      <!-- 有效范围: 0 ~ 15 (或其他特定于机器人的输入名称) -->
      <!-- 初期値: 0 -->
      <!-- 示例: 12 -->
    </field>
    <field name="input_state">
      <!-- input_state (入力検知状態): 等待的输入状态。 -->
      <!-- 有效范围: on (输入ON), off (输入OFF) -->
      <!-- 初期値: on -->
      <!-- 示例: on -->
    </field>
    <!-- <next> ... </next> -->
  </block>
</xml> 